bdd_lint/__init__.py
bdd_lint/config_verifier.py
bdd_lint/linter.py
bdd_lint/models/__init__.py
bdd_lint/models/issue.py
bdd_lint/parser/__init__.py
bdd_lint/parser/feature_parser.py
bdd_lint/rules/__init__.py
bdd_lint/rules/base_rule.py
bdd_lint/rules/consistent_step_keyword_order_rule.py
bdd_lint/rules/given_past_tense_rule.py
bdd_lint/rules/lower_case_feature_name_rule.py
bdd_lint/rules/lower_case_scenario_name_rule.py
bdd_lint/rules/max_scenarios_per_file_rule.py
bdd_lint/rules/max_steps_per_scenario_rule.py
bdd_lint/rules/no_duplicate_scenarios_rule.py
bdd_lint/rules/no_duplicate_step_rule.py
bdd_lint/rules/no_empty_scenarios_rule.py
bdd_lint/rules/no_multiline_step_rule.py
bdd_lint/rules/no_scenario_outlines_without_examples_rule.py
bdd_lint/rules/no_step_keyword_in_step_text_rule.py
bdd_lint/rules/no_tags_on_backgrounds_rule.py
bdd_lint/rules/no_unnamed_features_rule.py
bdd_lint/rules/no_unnamed_scenarios_rule.py
bdd_lint/rules/one_when_then_rule.py
bdd_lint/rules/required_tags_rule.py
bdd_lint/rules/tags_format_rule.py
bdd_lint/rules/tense_consistency_rule.py
bdd_lint/rules/then_future_tense_rule.py
bdd_lint/rules/third_person_rule.py
bdd_lint/rules/when_present_tense_rule.py
bdd_lint-0.1.0.dist-info/licenses/LICENSE
bdd_lint-0.1.0.dist-info/METADATA
bdd_lint-0.1.0.dist-info/WHEEL
bdd_lint-0.1.0.dist-info/entry_points.txt
bdd_lint-0.1.0.dist-info/top_level.txt
bdd_lint-0.1.0.dist-info/RECORD
