Metadata-Version: 2.4
Name: bdd-lint
Version: 0.1.0
Summary: A standalone linter for Gherkin feature files to enforce grammar and best practices
Requires-Python: >=3.7
License-File: LICENSE
Requires-Dist: PyYAML>=5.3.1
Provides-Extra: nlp
Requires-Dist: textblob; extra == "nlp"
Requires-Dist: spacy; extra == "nlp"
Requires-Dist: nltk; extra == "nlp"
Provides-Extra: test
Requires-Dist: pytest; extra == "test"
Requires-Dist: pytest-bdd; extra == "test"
Dynamic: description
Dynamic: description-content-type
Dynamic: license-file
Dynamic: provides-extra
Dynamic: requires-dist
Dynamic: requires-python
Dynamic: summary
